{
    "presenter_href": "https://dist1.github.io/ltaoist/", 
    "links": [
        {
            "text": "github.repo", 
            "href": "https://github.com/dist1/kuayingjianruanjianmiaoshuyuyan/"
        }, 
        {
            "text": "\u6587\u6863", 
            "href": "https://dist1.github.io/kuayingjianruanjianmiaoshuyuyan/"
        }
    ], 
    "ans_code": 1, 
    "simplified_name": "kuayingjianruanjianmiaoshuyuyan", 
    "introduction": "\u8de8\u786c\u4ef6\u8f6f\u4ef6\u63cf\u8ff0\u8bed\u8a00\u3002", 
    "submitted_time": 1563924158, 
    "presenter_text": "ltaoist", 
    "symbol_url": "https://dist1.github.io/kuayingjianruanjianmiaoshuyuyan/%E8%B7%A8%E7%A1%AC%E4%BB%B6%E8%BD%AF%E4%BB%B6%E6%8F%8F%E8%BF%B0%E8%AF%AD%E8%A8%80.png"
}